Compiled from "start.java"
public class start {
  public start();
    Code:
       0: aload_0
       1: invokespecial #1                  // Method java/lang/Object."<init>":()V
       4: return

  public static void main(java.lang.String[]);
    Code:
       0: getstatic     #2                  // Field java/lang/System.out:Ljava/io/PrintStream;
       3: ldc           #3                  // String Hallo Welt
       5: invokevirtual #4                  // Method java/io/PrintStream.println:(Ljava/lang/String;)V
       8: return

  int test1(int, int, int);
    Code:
       0: iload_1
       1: iload_2
       2: if_icmple     15
       5: iload_3
       6: iload_2
       7: if_icmpne     13
      10: bipush        78
      12: ireturn
      13: iload_1
      14: ireturn
      15: iload_1
      16: iconst_2
      17: imul
      18: iload_3
      19: if_icmple     26
      22: sipush        345
      25: ireturn
      26: iload_2
      27: ireturn

  int test2(int, int, int);
    Code:
       0: iconst_0
       1: istore        4
       3: iconst_0
       4: istore        5
       6: iload         5
       8: iload_3
       9: if_icmpge     57
      12: iload_1
      13: iload_2
      14: if_icmple     35
      17: iload_3
      18: iload_2
      19: if_icmpne     32
      22: iload         4
      24: bipush        78
      26: iadd
      27: istore        4
      29: goto          35
      32: iinc          4, -1
      35: iload_1
      36: iconst_2
      37: imul
      38: iload_3
      39: if_icmple     48
      42: iload_2
      43: istore        4
      45: goto          51
      48: iinc          4, -10
      51: iinc          5, 1
      54: goto          6
      57: iconst_2
      58: istore        5
      60: iload         5
      62: iload_1
      63: if_icmpge     75
      66: iinc          4, 2
      69: iinc          5, 1
      72: goto          60
      75: iload         4
      77: ireturn

  int test3(int, int);
    Code:
       0: bipush        10
       2: istore_3
       3: iload_1
       4: tableswitch   { // 0 to 4

                     0: 40

                     1: 42

                     2: 44

                     3: 60

                     4: 62
               default: 65
          }
      40: iconst_1
      41: istore_3
      42: iload_1
      43: istore_3
      44: iload_2
      45: bipush        10
      47: imul
      48: bipush        100
      50: if_icmpne     56
      53: iinc          1, 1
      56: iload_1
      57: iload_1
      58: imul
      59: istore_3
      60: iconst_3
      61: istore_3
      62: bipush        25
      64: istore_3
      65: iload_1
      66: iconst_1
      67: iadd
      68: istore_3
      69: bipush        10
      71: istore        4
      73: iload         4
      75: bipush        100
      77: if_icmpge     96
      80: iload_3
      81: iload_2
      82: iload         4
      84: iload         4
      86: imul
      87: isub
      88: iadd
      89: istore_3
      90: iinc          4, 1
      93: goto          73
      96: iload_3
      97: ireturn

  int test4(int, int);
    Code:
       0: bipush        10
       2: istore_3
       3: iload_1
       4: tableswitch   { // 0 to 4

                     0: 40

                     1: 42

                     2: 44

                     3: 74

                     4: 76
               default: 79
          }
      40: iconst_1
      41: istore_3
      42: iload_1
      43: istore_3
      44: iload_2
      45: bipush        10
      47: imul
      48: bipush        100
      50: if_icmpne     70
      53: iinc          1, 1
      56: iload_1
      57: iload_2
      58: iadd
      59: bipush        53
      61: if_icmple     70
      64: iload_1
      65: iconst_2
      66: iload_2
      67: imul
      68: iadd
      69: istore_1
      70: iload_1
      71: iload_1
      72: imul
      73: istore_3
      74: iconst_3
      75: istore_3
      76: bipush        25
      78: istore_3
      79: iload_1
      80: iconst_1
      81: iadd
      82: istore_3
      83: bipush        10
      85: istore        4
      87: iload         4
      89: bipush        100
      91: if_icmpge     110
      94: iload_3
      95: iload_2
      96: iload         4
      98: iload         4
     100: imul
     101: isub
     102: iadd
     103: istore_3
     104: iinc          4, 1
     107: goto          87
     110: iload_3
     111: ireturn

  int test5(int, int);
    Code:
       0: bipush        10
       2: istore_3
       3: iload_1
       4: tableswitch   { // 0 to 4

                     0: 40

                     1: 45

                     2: 50

                     3: 168

                     4: 170
               default: 173
          }
      40: iconst_1
      41: istore_3
      42: goto          177
      45: iload_1
      46: istore_3
      47: goto          177
      50: iload_2
      51: bipush        10
      53: imul
      54: bipush        100
      56: if_icmpne     161
      59: iinc          1, 1
      62: iload_1
      63: iload_2
      64: iadd
      65: bipush        53
      67: if_icmple     161
      70: iload_1
      71: iconst_2
      72: iload_2
      73: imul
      74: iadd
      75: istore_1
      76: bipush        10
      78: istore        4
      80: iload         4
      82: bipush        100
      84: if_icmpge     161
      87: iload_3
      88: iload_2
      89: iload         4
      91: iload         4
      93: imul
      94: isub
      95: iadd
      96: istore_3
      97: iload_3
      98: tableswitch   { // 1 to 3

                     1: 124

                     2: 129

                     3: 135
               default: 152
          }
     124: iconst_1
     125: istore_1
     126: goto          155
     129: bipush        10
     131: istore_2
     132: goto          155
     135: iload_2
     136: iload_1
     137: if_icmple     146
     140: bipush        100
     142: istore_2
     143: goto          155
     146: bipush        50
     148: istore_2
     149: goto          155
     152: bipush        15
     154: istore_1
     155: iinc          4, 1
     158: goto          80
     161: iload_1
     162: iload_1
     163: imul
     164: istore_3
     165: goto          177
     168: iconst_3
     169: istore_3
     170: bipush        25
     172: istore_3
     173: iload_1
     174: iconst_1
     175: iadd
     176: istore_3
     177: bipush        10
     179: istore        4
     181: iload         4
     183: bipush        100
     185: if_icmpge     204
     188: iload_3
     189: iload_2
     190: iload         4
     192: iload         4
     194: imul
     195: isub
     196: iadd
     197: istore_3
     198: iinc          4, 1
     201: goto          181
     204: iload_3
     205: ireturn

  int test6(int, int, int);
    Code:
       0: iload_1
       1: iload_2
       2: if_icmple     25
       5: iload_3
       6: iload_2
       7: if_icmpne     13
      10: bipush        78
      12: ireturn
      13: iload_3
      14: iload_2
      15: if_icmple     23
      18: iload_2
      19: bipush        10
      21: iadd
      22: istore_1
      23: iload_1
      24: ireturn
      25: iload_1
      26: iconst_2
      27: imul
      28: iload_3
      29: if_icmple     36
      32: sipush        345
      35: ireturn
      36: iload_2
      37: ireturn

  int test7(int, int);
    Code:
       0: bipush        10
       2: istore_3
       3: iload_1
       4: tableswitch   { // 0 to 4

                     0: 40

                     1: 45

                     2: 50

                     3: 168

                     4: 170
               default: 173
          }
      40: iconst_1
      41: istore_3
      42: goto          177
      45: iload_1
      46: istore_3
      47: goto          177
      50: iload_2
      51: bipush        10
      53: imul
      54: bipush        100
      56: if_icmpne     161
      59: iinc          1, 1
      62: iload_1
      63: iload_2
      64: iadd
      65: bipush        53
      67: if_icmple     161
      70: iload_1
      71: iconst_2
      72: iload_2
      73: imul
      74: iadd
      75: istore_1
      76: bipush        10
      78: istore        4
      80: iload         4
      82: bipush        100
      84: if_icmpge     161
      87: iload_3
      88: iload_2
      89: iload         4
      91: iload         4
      93: imul
      94: isub
      95: iadd
      96: istore_3
      97: iload_3
      98: tableswitch   { // 1 to 3

                     1: 124

                     2: 129

                     3: 135
               default: 152
          }
     124: iconst_1
     125: istore_1
     126: goto          155
     129: bipush        10
     131: istore_2
     132: goto          155
     135: iload_2
     136: iload_1
     137: if_icmple     146
     140: bipush        100
     142: istore_2
     143: goto          155
     146: bipush        50
     148: istore_2
     149: goto          155
     152: bipush        15
     154: istore_1
     155: iinc          4, 1
     158: goto          80
     161: iload_1
     162: iload_1
     163: imul
     164: istore_3
     165: goto          177
     168: iconst_3
     169: istore_3
     170: bipush        25
     172: istore_3
     173: iload_1
     174: iconst_1
     175: iadd
     176: istore_3
     177: iload_3
     178: ireturn

  int test8();
    Code:
       0: sipush        255
       3: istore_1
       4: bipush        20
       6: istore_2
       7: iconst_1
       8: istore_3
       9: iload_3
      10: ifeq          65
      13: iload_2
      14: iload_1
      15: iadd
      16: istore_2
      17: iconst_0
      18: istore        4
      20: iload         4
      22: iload_1
      23: if_icmpge     62
      26: bipush        10
      28: istore        5
      30: iload         5
      32: iload_1
      33: iload_1
      34: imul
      35: if_icmpge     56
      38: iload         5
      40: iload_1
      41: iload_1
      42: imul
      43: iconst_1
      44: isub
      45: if_icmpne     50
      48: iconst_0
      49: istore_3
      50: iinc          5, 1
      53: goto          30
      56: iinc          4, 1
      59: goto          20
      62: goto          9
      65: iload_2
      66: ireturn

  int test9(int, int);
    Code:
       0: iload_1
       1: iload_2
       2: if_icmplt     12
       5: iload_1
       6: iload_2
       7: if_icmple     12
      10: iload_1
      11: ireturn
      12: iload_2
      13: ireturn

  int test10(int, int);
    Code:
       0: iload_1
       1: iload_2
       2: if_icmplt     12
       5: iload_1
       6: iload_2
       7: if_icmple     12
      10: iload_1
      11: ireturn
      12: iload_2
      13: ireturn
}
